{"generatedAt":1712158337843,"generateTime":97,"contents":[{"_path":"/backend/b001","_dir":"backend","_draft":false,"_partial":false,"_locale":"","title":"Backend Installation","description":null,"image":null,"sequence":1,"category":"backend","link":null,"head":{"meta":[{"name":"keywords","content":""},{"name":"robots","content":""},{"name":"author","content":""},{"name":"copyright","content":"© 2024 A7新林口-社區網站"},{"name":"og:title","content":""}]},"publishedAt":"2024-04-02T00:00:00.000Z","toc":true,"body":{"type":"root","children":[{"type":"element","tag":"h2","props":{"id":"test-content"},"children":[{"type":"text","value":"Test Content"}]},{"type":"element","tag":"p","props":{},"children":[{"type":"element","tag":"img","props":{"alt":"b001-01.jpeg","src":"/images/backend/b001-01.jpeg"},"children":[]}]}],"toc":{"title":"","searchDepth":2,"depth":2,"links":[{"id":"test-content","depth":2,"text":"Test Content"}]}},"_type":"markdown","_id":"content:backend:b001.md","_source":"content","_file":"backend/b001.md","_extension":"md"},{"_path":"/basic/c001","_dir":"basic","_draft":false,"_partial":false,"_locale":"","title":"Basic Installation","description":null,"image":null,"sequence":1,"category":"Basic","link":null,"head":{"meta":[{"name":"keywords","content":""},{"name":"robots","content":""},{"name":"author","content":""},{"name":"copyright","content":"© 2024 A7新林口-社區網站"},{"name":"og:title","content":""}]},"publishedAt":"2024-04-02T00:00:00.000Z","toc":true,"body":{"type":"root","children":[{"type":"element","tag":"h2","props":{"id":"test-content"},"children":[{"type":"text","value":"Test Content"}]},{"type":"element","tag":"p","props":{},"children":[{"type":"element","tag":"img","props":{"alt":"c001-01.jpeg","src":"/images/basic/c001-01.jpeg"},"children":[]}]}],"toc":{"title":"","searchDepth":2,"depth":2,"links":[{"id":"test-content","depth":2,"text":"Test Content"}]}},"_type":"markdown","_id":"content:basic:c001.md","_source":"content","_file":"basic/c001.md","_extension":"md"},{"_path":"/frontend/f001","_dir":"frontend","_draft":false,"_partial":false,"_locale":"","title":"Nuxt Installation","description":null,"image":null,"sequence":1,"category":"Nuxt.js","link":null,"head":{"meta":[{"name":"keywords","content":""},{"name":"robots","content":""},{"name":"author","content":""},{"name":"copyright","content":"© 2024 A7新林口-社區網站"},{"name":"og:title","content":""}]},"publishedAt":"2024-04-02T00:00:00.000Z","toc":true,"body":{"type":"root","children":[{"type":"element","tag":"h2","props":{"id":"test-content"},"children":[{"type":"text","value":"Test Content"}]},{"type":"element","tag":"p","props":{},"children":[{"type":"element","tag":"img","props":{"alt":"f001-01.jpeg","src":"/images/frontend/f001-01.jpeg"},"children":[]}]}],"toc":{"title":"","searchDepth":2,"depth":2,"links":[{"id":"test-content","depth":2,"text":"Test Content"}]}},"_type":"markdown","_id":"content:frontend:f001.md","_source":"content","_file":"frontend/f001.md","_extension":"md"},{"_path":"/inheritance/i001","_dir":"inheritance","_draft":false,"_partial":false,"_locale":"","title":"Inheritance Installation","description":null,"image":null,"sequence":1,"category":"Inheritance","link":null,"head":{"meta":[{"name":"keywords","content":""},{"name":"robots","content":""},{"name":"author","content":""},{"name":"copyright","content":"© 2024 A7新林口-社區網站"},{"name":"og:title","content":""}]},"publishedAt":"2024-04-02T00:00:00.000Z","toc":true,"body":{"type":"root","children":[{"type":"element","tag":"h2","props":{"id":"test-content"},"children":[{"type":"text","value":"Test Content"}]},{"type":"element","tag":"p","props":{},"children":[{"type":"element","tag":"img","props":{"alt":"i001-01.jpeg","src":"/images/inheritance/i001-01.jpeg"},"children":[]}]}],"toc":{"title":"","searchDepth":2,"depth":2,"links":[{"id":"test-content","depth":2,"text":"Test Content"}]}},"_type":"markdown","_id":"content:inheritance:i001.md","_source":"content","_file":"inheritance/i001.md","_extension":"md"},{"_path":"/market/m001","_dir":"market","_draft":false,"_partial":false,"_locale":"","title":"Market Installation","description":null,"image":null,"sequence":1,"category":"Market","link":null,"head":{"meta":[{"name":"keywords","content":""},{"name":"robots","content":""},{"name":"author","content":""},{"name":"copyright","content":"© 2024 A7新林口-社區網站"},{"name":"og:title","content":""}]},"publishedAt":"2024-04-02T00:00:00.000Z","toc":true,"body":{"type":"root","children":[{"type":"element","tag":"h2","props":{"id":"test-content"},"children":[{"type":"text","value":"Test Content"}]},{"type":"element","tag":"p","props":{},"children":[{"type":"element","tag":"img","props":{"alt":"m001-01.jpeg","src":"/images/market/m001-01.jpeg"},"children":[]}]}],"toc":{"title":"","searchDepth":2,"depth":2,"links":[{"id":"test-content","depth":2,"text":"Test Content"}]}},"_type":"markdown","_id":"content:market:m001.md","_source":"content","_file":"market/m001.md","_extension":"md"},{"_path":"/planning/p001","_dir":"planning","_draft":false,"_partial":false,"_locale":"","title":"Planning Installation","description":null,"image":null,"sequence":1,"category":"Planning","link":null,"head":{"meta":[{"name":"keywords","content":""},{"name":"robots","content":""},{"name":"author","content":""},{"name":"copyright","content":"© 2024 A7新林口-社區網站"},{"name":"og:title","content":""}]},"publishedAt":"2024-04-02T00:00:00.000Z","toc":true,"body":{"type":"root","children":[{"type":"element","tag":"h2","props":{"id":"test-content"},"children":[{"type":"text","value":"Test Content"}]},{"type":"element","tag":"p","props":{},"children":[{"type":"element","tag":"img","props":{"alt":"p001-01.jpeg","src":"/images/planning/p001-01.jpeg"},"children":[]}]}],"toc":{"title":"","searchDepth":2,"depth":2,"links":[{"id":"test-content","depth":2,"text":"Test Content"}]}},"_type":"markdown","_id":"content:planning:p001.md","_source":"content","_file":"planning/p001.md","_extension":"md"}],"navigation":[{"title":"Backend","_path":"/backend","children":[{"title":"Backend Installation","_path":"/backend/b001"}]},{"title":"Basic","_path":"/basic","children":[{"title":"Basic Installation","_path":"/basic/c001"}]},{"title":"Frontend","_path":"/frontend","children":[{"title":"Nuxt Installation","_path":"/frontend/f001"}]},{"title":"Inheritance","_path":"/inheritance","children":[{"title":"Inheritance Installation","_path":"/inheritance/i001"}]},{"title":"Market","_path":"/market","children":[{"title":"Market Installation","_path":"/market/m001"}]},{"title":"Planning","_path":"/planning","children":[{"title":"Planning Installation","_path":"/planning/p001"}]}]}